saltext/relenv/__init__.py
saltext/relenv/loader.py
saltext/relenv/version.py
saltext/relenv/modules/__init__.py
saltext/relenv/modules/relenv_mod.py
saltext/relenv/states/__init__.py
saltext/relenv/states/relenv_mod.py
saltext_relenv-0.1.3.dist-info/licenses/LICENSE
saltext_relenv-0.1.3.dist-info/METADATA
saltext_relenv-0.1.3.dist-info/WHEEL
saltext_relenv-0.1.3.dist-info/entry_points.txt
saltext_relenv-0.1.3.dist-info/top_level.txt
saltext_relenv-0.1.3.dist-info/RECORD
