Metadata-Version: 2.4
Name: saltext.relenv
Version: 0.1.3
Summary: Salt Extension for interacting with Relenv
Home-page: https://github.com/Akm0d/saltext-relenv
Author: Tyler Levy Conde
Author-email: tyler.levy-conde@broadcom.com
Project-URL: Source, https://github.com/Akm0d/saltext-relenv
Project-URL: Tracker, https://github.com/Akm0d/saltext-relenv/issues
Keywords: salt-extension
Platform: any
Classifier: Programming Language :: Python
Classifier: Programming Language :: Cython
Classifier: Programming Language :: Python :: 3
Classifier: Programming Language :: Python :: 3 :: Only
Classifier: Programming Language :: Python :: 3.5
Classifier: Programming Language :: Python :: 3.6
Classifier: Programming Language :: Python :: 3.7
Classifier: Programming Language :: Python :: 3.8
Classifier: Programming Language :: Python :: 3.9
Classifier: Development Status :: 4 - Beta
Classifier: Intended Audience :: Developers
Requires-Python: >=3.5
License-File: LICENSE
Requires-Dist: salt>=3006
Requires-Dist: relenv>=0.19.0
Dynamic: license-file
